hkscs_unicode_converter/__init__.py
hkscs_unicode_converter/converter.py
hkscs_unicode_converter/data/__init__.py
hkscs_unicode_converter/data/config.json
hkscs_unicode_converter/data/gccs.tsv
hkscs_unicode_converter/data/hkscs1999.tsv
hkscs_unicode_converter/data/hkscs2001.tsv
hkscs_unicode_converter/data/hkscs2001_2.tsv
hkscs_unicode_converter/data/hkscs2004.tsv
hkscs_unicode_converter/data/hkscs2008.tsv
hkscs_unicode_converter/data/hkscs2016.json
hkscs_unicode_converter/test/__init__.py
hkscs_unicode_converter/test/test_char.py
hkscs_unicode_converter/test/test_string.py
hkscs_unicode_converter-1.1.0.dist-info/LICENSE
hkscs_unicode_converter-1.1.0.dist-info/METADATA
hkscs_unicode_converter-1.1.0.dist-info/WHEEL
hkscs_unicode_converter-1.1.0.dist-info/top_level.txt
hkscs_unicode_converter-1.1.0.dist-info/RECORD
