Metadata-Version: 2.1
Name: hkscs-unicode-converter
Version: 1.1.0
Summary: Convert HKSCS codepoints to corresponding new codepoints in Unicode 4.1 onwards
Home-page: https://github.com/aaronhktan/hkscs-unicode-converter
Author: Aaron Tan
Author-email: hi@aaronhktan.com
License: UNKNOWN
Project-URL: Bug Tracker, https://github.com/aaronhktan/hkscs-unicode-converter/issues
Project-URL: Source Code, https://github.com/aaronhktan/hkscs-unicode-converter
Platform: UNKNOWN
Classifier: Programming Language :: Python :: 3
Classifier: License :: OSI Approved :: MIT License
Classifier: Operating System :: OS Independent
Requires-Python: >=3.7
License-File: LICENSE
